sushy_oem_idrac/__init__.py
sushy_oem_idrac/asynchronous.py
sushy_oem_idrac/constants.py
sushy_oem_idrac/utils.py
sushy_oem_idrac/resources/__init__.py
sushy_oem_idrac/resources/attributes.py
sushy_oem_idrac/resources/manager/__init__.py
sushy_oem_idrac/resources/manager/constants.py
sushy_oem_idrac/resources/manager/idrac_card_service.py
sushy_oem_idrac/resources/manager/job_collection.py
sushy_oem_idrac/resources/manager/job_service.py
sushy_oem_idrac/resources/manager/lifecycle_service.py
sushy_oem_idrac/resources/manager/manager.py
sushy_oem_idrac/resources/system/constants.py
sushy_oem_idrac/resources/system/raid_service.py
sushy_oem_idrac/resources/system/system.py
sushy_oem_idrac/resources/system/storage/constants.py
sushy_oem_idrac/resources/system/storage/controller.py
sushy_oem_idrac/resources/taskservice/constants.py
sushy_oem_idrac/resources/taskservice/task.py
sushy_oem_idrac/tests/__init__.py
sushy_oem_idrac/tests/functional/__init__.py
sushy_oem_idrac/tests/functional/vmedia_boot.py
sushy_oem_idrac/tests/unit/__init__.py
sushy_oem_idrac/tests/unit/base.py
sushy_oem_idrac/tests/unit/test_asynchronous.py
sushy_oem_idrac/tests/unit/test_root.py
sushy_oem_idrac/tests/unit/json_samples/error_pending_job.json
sushy_oem_idrac/tests/unit/json_samples/error_running_job.json
sushy_oem_idrac/tests/unit/json_samples/export_configuration_idrac.json
sushy_oem_idrac/tests/unit/json_samples/export_configuration_nic_bios.json
sushy_oem_idrac/tests/unit/json_samples/idrac_card_service.json
sushy_oem_idrac/tests/unit/json_samples/job_collection_expanded.json
sushy_oem_idrac/tests/unit/json_samples/job_service.json
sushy_oem_idrac/tests/unit/json_samples/lifecycle_service.json
sushy_oem_idrac/tests/unit/json_samples/manager.json
sushy_oem_idrac/tests/unit/json_samples/manager_collection.json
sushy_oem_idrac/tests/unit/json_samples/raid_service.json
sushy_oem_idrac/tests/unit/json_samples/root.json
sushy_oem_idrac/tests/unit/json_samples/storage_controller.json
sushy_oem_idrac-6.0.0.dist-info/AUTHORS
sushy_oem_idrac-6.0.0.dist-info/LICENSE
sushy_oem_idrac-6.0.0.dist-info/METADATA
sushy_oem_idrac-6.0.0.dist-info/WHEEL
sushy_oem_idrac-6.0.0.dist-info/entry_points.txt
sushy_oem_idrac-6.0.0.dist-info/pbr.json
sushy_oem_idrac-6.0.0.dist-info/top_level.txt
sushy_oem_idrac-6.0.0.dist-info/RECORD
