Metadata-Version: 2.1
Name: sushy-oem-idrac
Version: 6.0.0
Summary: Dell EMC iDRAC OEM extension package for the sushy library
Home-page: https://docs.openstack.org/sushy/latest/
Author: OpenStack
Author-email: openstack-discuss@lists.openstack.org
License: UNKNOWN
Platform: UNKNOWN
Classifier: Environment :: OpenStack
Classifier: Intended Audience :: Information Technology
Classifier: Intended Audience :: System Administrators
Classifier: License :: OSI Approved :: Apache Software License
Classifier: Operating System :: POSIX :: Linux
Classifier: Programming Language :: Python
Classifier: Programming Language :: Python :: 3 :: Only
Classifier: Programming Language :: Python :: 3
Classifier: Programming Language :: Python :: 3.8
Classifier: Programming Language :: Python :: 3.9
Classifier: Programming Language :: Python :: 3.10
Classifier: Programming Language :: Python :: 3.11
Requires-Python: >=3.8
Requires-Dist: pbr (!=2.1.0,>=2.0.0)
Requires-Dist: python-dateutil (>=2.7.0)
Requires-Dist: sushy (>=4.0.0)
